LICENSE
MANIFEST.in
README.rst
setup.py
shadowsocksr_cli/__init__.py
shadowsocksr_cli/common.py
shadowsocksr_cli/functions.py
shadowsocksr_cli/handle_utils.py
shadowsocksr_cli/http_utils.py
shadowsocksr_cli/init_utils.py
shadowsocksr_cli/logger.py
shadowsocksr_cli/main.py
shadowsocksr_cli/network_test_utils.py
shadowsocksr_cli/parse_utils.py
shadowsocksr_cli/print_utils.py
shadowsocksr_cli/setting_utils.py
shadowsocksr_cli/speedtest.py
shadowsocksr_cli/update_utils.py
shadowsocksr_cli/vmess2json.py
shadowsocksr_cli.egg-info/PKG-INFO
shadowsocksr_cli.egg-info/SOURCES.txt
shadowsocksr_cli.egg-info/dependency_links.txt
shadowsocksr_cli.egg-info/entry_points.txt
shadowsocksr_cli.egg-info/requires.txt
shadowsocksr_cli.egg-info/top_level.txt
shadowsocksr_cli/shadowsocks/__init__.py
shadowsocksr_cli/shadowsocks/asyncdns.py
shadowsocksr_cli/shadowsocks/common.py
shadowsocksr_cli/shadowsocks/daemon.py
shadowsocksr_cli/shadowsocks/encrypt.py
shadowsocksr_cli/shadowsocks/encrypt_test.py
shadowsocksr_cli/shadowsocks/eventloop.py
shadowsocksr_cli/shadowsocks/local.py
shadowsocksr_cli/shadowsocks/lru_cache.py
shadowsocksr_cli/shadowsocks/manager.py
shadowsocksr_cli/shadowsocks/obfs.py
shadowsocksr_cli/shadowsocks/ordereddict.py
shadowsocksr_cli/shadowsocks/server.py
shadowsocksr_cli/shadowsocks/shell.py
shadowsocksr_cli/shadowsocks/tcprelay.py
shadowsocksr_cli/shadowsocks/udprelay.py
shadowsocksr_cli/shadowsocks/version.py
shadowsocksr_cli/shadowsocks/crypto/__init__.py
shadowsocksr_cli/shadowsocks/crypto/ctypes_libsodium.py
shadowsocksr_cli/shadowsocks/crypto/ctypes_openssl.py
shadowsocksr_cli/shadowsocks/crypto/openssl.py
shadowsocksr_cli/shadowsocks/crypto/rc4_md5.py
shadowsocksr_cli/shadowsocks/crypto/sodium.py
shadowsocksr_cli/shadowsocks/crypto/table.py
shadowsocksr_cli/shadowsocks/crypto/util.py
shadowsocksr_cli/shadowsocks/obfsplugin/__init__.py
shadowsocksr_cli/shadowsocks/obfsplugin/auth.py
shadowsocksr_cli/shadowsocks/obfsplugin/auth_chain.py
shadowsocksr_cli/shadowsocks/obfsplugin/http_simple.py
shadowsocksr_cli/shadowsocks/obfsplugin/obfs_tls.py
shadowsocksr_cli/shadowsocks/obfsplugin/plain.py
shadowsocksr_cli/shadowsocks/obfsplugin/verify.py